{
  "stats": {
    "suites": 0,
    "tests": 1,
    "passes": 1,
    "pending": 0,
    "failures": 0,
    "start": "2025-10-29T21:05:26.298Z",
    "end": "2025-10-29T21:05:27.238Z",
    "duration": 940,
    "testsRegistered": 1,
    "passPercent": 100,
    "pendingPercent": 0,
    "other": 0,
    "hasOther": false,
    "skipped": 0,
    "hasSkipped": false
  },
  "results": [
    {
      "uuid": "d2dc9ee4-058c-4c89-b26a-15e4f52ae498",
      "title": "",
      "fullFile": "",
      "file": "C:\\_Repositorio\\01_Projetos\\ebac-m24-pactumjs-tests-api\\teste\\contract\\contratoCategoria\\apiAddCategoria.test.js",
      "beforeHooks": [
        {
          "title": "\"before all\" hook in \"{root}\"",
          "fullTitle": "\"before all\" hook in \"{root}\"",
          "timedOut": false,
          "duration": 6,
          "state": null,
          "speed": null,
          "pass": false,
          "fail": false,
          "pending": false,
          "context": null,
          "code": "addFlowReporter();\nawait mock.start(4000);",
          "err": {},
          "uuid": "976816d1-bdf8-4d88-8e44-38cc7c1f6722",
          "parentUUID": "d2dc9ee4-058c-4c89-b26a-15e4f52ae498",
          "isHook": true,
          "skipped": false
        },
        {
          "title": "\"before each\" hook in \"{root}\"",
          "fullTitle": "\"before each\" hook in \"{root}\"",
          "timedOut": false,
          "duration": 420,
          "state": null,
          "speed": null,
          "pass": false,
          "fail": false,
          "pending": false,
          "context": null,
          "code": "token = await gerarToken();",
          "err": {},
          "uuid": "3c97507e-099a-4a93-9db7-4b10e083fe2a",
          "parentUUID": "d2dc9ee4-058c-4c89-b26a-15e4f52ae498",
          "isHook": true,
          "skipped": false
        }
      ],
      "afterHooks": [
        {
          "title": "\"after all\" hook in \"{root}\"",
          "fullTitle": "\"after all\" hook in \"{root}\"",
          "timedOut": false,
          "duration": 362,
          "state": null,
          "speed": null,
          "pass": false,
          "fail": false,
          "pending": false,
          "context": null,
          "code": "await mock.stop();\nawait reporter.end();",
          "err": {},
          "uuid": "20410f90-d1f5-458a-b9d6-15621571d7a7",
          "parentUUID": "d2dc9ee4-058c-4c89-b26a-15e4f52ae498",
          "isHook": true,
          "skipped": false
        }
      ],
      "tests": [
        {
          "title": "API - Teste de Contrato - Adicionar categoria",
          "fullTitle": "API - Teste de Contrato - Adicionar categoria",
          "timedOut": false,
          "duration": 142,
          "state": "passed",
          "speed": "slow",
          "pass": true,
          "fail": false,
          "pending": false,
          "context": null,
          "code": "const categoriaFake = factory.categoria(); // gera dados dinâmicos\n    await flow('Cadastrar Categoria')\n        .post('http://lojaebac.ebaconline.art.br/api/addCategory')\n        .withHeaders('Authorization', token)\n        .withJson(categoriaFake)\n        .expectStatus(200)\n        .expectJson('success', true)\n        .expectJson('message', 'category added')\n        .expectJsonMatch({\n            data: {\n                _id: regex(/^[a-f0-9]{24}$/), // valida formato do ID\n                name: like('Nome da Categoria'),\n                photo: like('fotoCategoria.png.com.br'),\n            },\n        });",
          "err": {},
          "uuid": "ca18a153-6170-49a3-874d-9caf79f15e36",
          "parentUUID": "d2dc9ee4-058c-4c89-b26a-15e4f52ae498",
          "isHook": false,
          "skipped": false
        }
      ],
      "suites": [],
      "passes": [
        "ca18a153-6170-49a3-874d-9caf79f15e36"
      ],
      "failures": [],
      "pending": [],
      "skipped": [],
      "duration": 142,
      "root": true,
      "rootEmpty": false,
      "_timeout": 2000
    }
  ],
  "meta": {
    "mocha": {
      "version": "11.7.4"
    },
    "mochawesome": {
      "options": {
        "quiet": true,
        "reportFilename": "contratoApiCat-report",
        "saveHtml": false,
        "saveJson": true,
        "consoleReporter": "spec",
        "useInlineDiffs": false,
        "code": true
      },
      "version": "7.1.4"
    },
    "marge": {
      "options": {
        "reportDir": "reports/mocha",
        "reportFilename": "contratoApiCat-report",
        "json": "true",
        "html": "false",
        "quiet": "true"
      },
      "version": "6.3.0"
    }
  }
}